takumi_http/__init__.py
takumi_http/__version__.py
takumi_http/_compat.py
takumi_http/_json.py
takumi_http/exc.py
takumi_http/http_handler.py
takumi_http/protocol.py
takumi_http/session.py
takumi_http/testing.py
takumi_http/utils.py
takumi_http-0.1.7.dist-info/LICENSE
takumi_http-0.1.7.dist-info/METADATA
takumi_http-0.1.7.dist-info/WHEEL
takumi_http-0.1.7.dist-info/top_level.txt
takumi_http-0.1.7.dist-info/RECORD
