Metadata-Version: 2.1
Name: takumi-http
Version: 0.1.7
Summary: Http to thrift protocol conversion
Home-page: https://github.com/elemepi/takumi-http
Author: Eleme Lab
Author-email: imaralla@icloud.com
License: UNKNOWN
Platform: UNKNOWN
Requires-Dist: takumi
Requires-Dist: takumi-config
Requires-Dist: takumi-thrift
Requires-Dist: thriftpy
Requires-Dist: itsdangerous
